src/__init__.py
src/__main__.py
src/server.py
ml_training_init_mcp-0.2.2.dist-info/METADATA
ml_training_init_mcp-0.2.2.dist-info/WHEEL
ml_training_init_mcp-0.2.2.dist-info/entry_points.txt
ml_training_init_mcp-0.2.2.dist-info/RECORD
