Metadata-Version: 2.4
Name: ml-training-init-mcp
Version: 0.2.2
Summary: MCP server for ML training script initialization with file locking
Author: ML Training Init
License: MIT
Requires-Python: >=3.10
Requires-Dist: httpx>=0.27.0
Requires-Dist: mcp>=1.0.0
